[
    {
        "id": 1,
        "title": "Bombay Sapphire 750ml",
        "subtitle": "750ml",
        "price": 31955,
        "image": "https://media.tada.com.ar/product_variant/00003629_8b32a26d-78d8-4488-bbaa-e81335fe02fe.jpg?w=100&h=100",
        "categoryId": 2,
        "description": "Bombay Sapphire es una ginebra de primera calidad con un sabor floral y a enebro, ideal para gin tonic.",
        "discount": 10,
        "deliveryType": "Inmediata",
        "brand": "Bombay",
        "tags": ["gin", "premium", "botella"],
        "stock": 300
    },
    {
        "id": 2,
        "title": "Absolut Original 750ml",
        "subtitle": "750ml",
        "price": 35106,
        "image": "https://media.tada.com.ar/product_variant/00003629_8b32a26d-78d8-4488-bbaa-e81335fe02fe.jpg?w=100&h=100",
        "categoryId": 2,
        "description": "Vodka Absolut Original, suave y versátil, ideal para cócteles y mezclas.",
        "discount": 15,
        "deliveryType": "Diferida",
        "brand": "Absolut",
        "tags": ["vodka", "premium", "original"],
        "stock": 500
    },
    {
        "id": 3,
        "title": "Bombay Sapphire 750ml",
        "subtitle": "Botella",
        "price": 31955,
        "image": "https://media.tada.com.ar/product_variant/00003628_554bf26c-5c94-4f53-8e88-cc72a98d3c9b.jpg?w=100&h=100",
        "categoryId": 2,
        "description": "Bombay Sapphire es conocido por sus ingredientes botánicos que lo hacen especial para cualquier ocasión.",
        "discount": 5,
        "deliveryType": "Inmediata",
        "brand": "Bombay",
        "tags": ["gin", "botánicos", "bebida"],
        "stock": 250
    },
    {
        "id": 4,
        "title": "Bombay Sapphire 750ml",
        "subtitle": "Botella",
        "price": 31955,
        "image": "https://media.tada.com.ar/product_variant/00003628_554bf26c-5c94-4f53-8e88-cc72a98d3c9b.jpg?w=100&h=100",
        "categoryId": 2,
        "description": "Una ginebra sofisticada con un perfil único, perfecta para tragos elegantes.",
        "discount": 8,
        "deliveryType": "Inmediata",
        "brand": "Bombay",
        "tags": ["gin", "floral", "premium"],
        "stock": 200
    },
    {
        "id": 5,
        "title": "Cerveza Quilmes Sin alcohol",
        "subtitle": "Lata 473ml",
        "price": 800,
        "image": "https://media.tada.com.ar/product_variant/00003628_554bf26c-5c94-4f53-8e88-cc72a98d3c9b.jpg?w=100&h=100",
        "categoryId": 1,
        "description": "Cerveza Quilmes sin alcohol, el sabor de siempre sin comprometer el estilo de vida.",
        "discount": 0,
        "deliveryType": "Inmediata",
        "brand": "Quilmes",
        "tags": ["cerveza", "sin alcohol", "lager"],
        "stock": 1000
    },
    {
        "id": 6,
        "title": "Cerveza Andes Origen Rubia",
        "subtitle": "Botella 330ml",
        "price": 950,
        "image": "https://media.tada.com.ar/product_variant/00003628_554bf26c-5c94-4f53-8e88-cc72a98d3c9b.jpg?w=100&h=100",
        "categoryId": 1,
        "description": "Cerveza Andes Origen Rubia, con el auténtico sabor a malta y un toque refrescante.",
        "discount": 10,
        "deliveryType": "Diferida",
        "brand": "Andes",
        "tags": ["cerveza", "rubia", "lager"],
        "stock": 800
    },
    {
        "id": 7,
        "title": "Cerveza Quilmes Sin alcohol",
        "subtitle": "Lata 473ml",
        "price": 810,
        "image": "https://media.tada.com.ar/product_variant/00003628_554bf26c-5c94-4f53-8e88-cc72a98d3c9b.jpg?w=100&h=100",
        "categoryId": 1,
        "description": "Una opción ligera para los que buscan disfrutar sin efectos de alcohol.",
        "discount": 5,
        "deliveryType": "Inmediata",
        "brand": "Quilmes",
        "tags": ["cerveza", "sin alcohol", "lager"],
        "stock": 700
    },
    {
        "id": 8,
        "title": "Cerveza Andes Origen Rubia",
        "subtitle": "Botella 330ml",
        "price": 970,
        "image": "https://media.tada.com.ar/product_variant/00003628_554bf26c-5c94-4f53-8e88-cc72a98d3c9b.jpg?w=100&h=100",
        "categoryId": 1,
        "description": "Disfruta de Andes Rubia, con un sabor suave y refrescante, perfecta para cualquier ocasión.",
        "discount": 12,
        "deliveryType": "Inmediata",
        "brand": "Andes",
        "tags": ["cerveza", "rubia", "malta"],
        "stock": 500
    },
    {
        "id": 9,
        "title": "Cerveza Quilmes Sin alcohol",
        "subtitle": "Lata 473ml",
        "price": 820,
        "image": "https://media.tada.com.ar/product_variant/00003628_554bf26c-5c94-4f53-8e88-cc72a98d3c9b.jpg?w=100&h=100",
        "categoryId": 1,
        "description": "Cerveza refrescante sin alcohol, con el mismo sabor que amas.",
        "discount": 0,
        "deliveryType": "Diferida",
        "brand": "Quilmes",
        "tags": ["cerveza", "sin alcohol", "lager"],
        "stock": 400
    },
    {
        "id": 10,
        "title": "Cerveza Andes Origen Rubia",
        "subtitle": "Botella 330ml",
        "price": 960,
        "image": "https://media.tada.com.ar/product_variant/00003628_554bf26c-5c94-4f53-8e88-cc72a98d3c9b.jpg?w=100&h=100",
        "categoryId": 1,
        "description": "Una cerveza rubia con un toque de malta, perfecta para acompañar tus mejores momentos.",
        "discount": 5,
        "deliveryType": "Inmediata",
        "brand": "Andes",
        "tags": ["cerveza", "rubia", "refrescante"],
        "stock": 300
    },
    {
        "id": 11,
        "title": "Bombay Sapphire 750ml",
        "subtitle": "750ml",
        "price": 31955,
        "image": "https://media.tada.com.ar/product_variant/00003628_554bf26c-5c94-4f53-8e88-cc72a98d3c9b.jpg?w=100&h=100",
        "categoryId": 2,
        "description": "Una ginebra premium, suave y equilibrada con aromas botánicos.",
        "discount": 10,
        "deliveryType": "Diferida",
        "brand": "Bombay",
        "tags": ["gin", "premium", "aromático"],
        "stock": 150
    },
    {
        "id": 12,
        "title": "Absolut Original 750ml",
        "subtitle": "750ml",
        "price": 35106,
        "image": "https://media.tada.com.ar/product_variant/00003629_8b32a26d-78d8-4488-bbaa-e81335fe02fe.jpg?w=100&h=100",
        "categoryId": 2,
        "description": "Vodka sueco de calidad superior, ideal para cualquier ocasión.",
        "discount": 20,
        "deliveryType": "Inmediata",
        "brand": "Absolut",
        "tags": ["vodka", "sueco", "original"],
        "stock": 120
    },
    {
        "id": 13,
        "title": "Cerveza Quilmes Sin alcohol",
        "subtitle": "Lata 473ml",
        "price": 830,
        "image": "https://media.tada.com.ar/product_variant/quilmes_sin_alcohol.jpg?w=100&h=100",
        "categoryId": 1,
        "description": "Cerveza clásica sin alcohol, mantiene el sabor de Quilmes.",
        "discount": 0,
        "deliveryType": "Diferida",
        "brand": "Quilmes",
        "tags": ["cerveza", "sin alcohol", "clásica"],
        "stock": 600
    },
    {
        "id": 14,
        "title": "Cerveza Andes Origen Rubia",
        "subtitle": "Botella 330ml",
        "price": 940,
        "image": "https://media.tada.com.ar/product_variant/andes_origen_rubia.jpg?w=100&h=100",
        "categoryId": 1,
        "description": "Cerveza rubia refrescante, fabricada con ingredientes de origen.",
        "discount": 8,
        "deliveryType": "Inmediata",
        "brand": "Andes",
        "tags": ["cerveza", "rubia", "lager"],
        "stock": 550
    },
    {
        "id": 15,
        "title": "Cerveza Quilmes Sin alcohol",
        "subtitle": "Lata 473ml",
        "price": 810,
        "image": "https://media.tada.com.ar/product_variant/quilmes_sin_alcohol.jpg?w=100&h=100",
        "categoryId": 1,
        "description": "Una cerveza sin alcohol que acompaña tus momentos cotidianos.",
        "discount": 0,
        "deliveryType": "Diferida",
        "brand": "Quilmes",
        "tags": ["cerveza", "sin alcohol", "refrescante"],
        "stock": 700
    }
]
